<?xml version="1.0" encoding="UTF-8"?>


<?xml-stylesheet type="text/xsl" href="fclase.xsl"?>
<grupo grupo="DAW1">
  <profesorado>
    <profesor tutor="si">
      <nombreProfesor>Fran Cisco</nombreProfesor>
      <responsable id="DAW-LMSGI">LMSGI</responsable>
      <responsable id="DAW-Sistemas">Sistemas</responsable>
    </profesor>
    <profesor tutor="no">
      <nombreProfesor>Ana Frank</nombreProfesor>
      <responsable id="DAW-FOL">FOL</responsable>
    </profesor>
    <profesor>
      <nombreProfesor>David Darwing</nombreProfesor>
      <responsable id="DAW-ING">Inglés</responsable>
    </profesor>
  </profesorado>
  <clase>
    <aula>INFORMATICA 2</aula>
    <alumno repetidor="si">
      <nombre>Ana Diosdado</nombre>
      <alias file="ana.png"></alias>
      <media>7.3</media>
      <modulos>
        <modulo idref="DAW-LMSGI">LMSGI</modulo>
        <modulo idref="DAW-Sistemas">Sistemas</modulo>
        <modulo idref="DAW-FOL">FOL</modulo>
      </modulos>
    </alumno>
    <alumno repetidor="si">
      <nombre>Carlos Larrañaga </nombre>
      <alias file="carlos.png">Carlos</alias>
      <media>9.1</media>
      <modulos>
        <modulo idref="DAW-LMSGI">LMSGI</modulo>
        <modulo idref="DAW-Sistemas">Sistemas</modulo>
        <modulo idref="DAW-FOL">FOL</modulo>
      </modulos>
    </alumno>
    <alumno repetidor="si">
      <nombre>Frank de la Jungla  </nombre>
      <alias file="frank.png">Frank</alias>
      <media>6.1</media>
      <modulos>
        <modulo idref="DAW-LMSGI">LMSGI</modulo>
        <modulo idref="DAW-Sistemas">Sistemas</modulo>
        <modulo idref="DAW-FOL">FOL</modulo>
      </modulos>
    </alumno>
    <alumno repetidor="si">
      <nombre>Sergio Fabregas</nombre>
      <alias file="ana.png"></alias>
      <media>8.3</media>
      <modulos>

        <modulo idref="DAW-FOL">FOL</modulo>
      </modulos>
    </alumno>
    <alumno repetidor="si">
      <nombre>Mónica Artero</nombre>
      <alias file="ana.png">Moni</alias>
      <media>7.9</media>
      <modulos>
        <modulo idref="DAW-Sistemas">Sistemas</modulo>
 
      </modulos>
    </alumno>
    <alumno repetidor="si">
      <nombre>Olga Soler </nombre>
      <alias file="ana.png">Olga</alias>
      <media>5.3</media>
      <modulos>
        <modulo idref="DAW-LMSGI">LMSGI</modulo>

        <modulo idref="DAW-FOL">FOL</modulo>
      </modulos>
    </alumno>
  </clase>
</grupo>
